airtest_ext/airtest_bot.py
airtest_ext/bot_template.py
airtest_ext/debug_wnd.py
airtest_ext/dpgapp.py
airtest_ext/interceptor_mgr.py
airtest_ext/mitm_callback.py
airtest_ext/mitmproxy_svr.py
airtest_ext/page.py
airtest_ext/template.py
airtest_ext/utils.py
airtest_ext/cert/mitmproxy-ca-cert.cer
airtest_ext/cert/mitmproxy-ca-cert.p12
airtest_ext/cert/mitmproxy-ca-cert.pem
airtest_ext/cert/mitmproxy-ca.p12
airtest_ext/cert/mitmproxy-ca.pem
airtest_ext/cert/mitmproxy-dhparam.pem
airtest_ext/resource/OPPOSans-M.ttf
airtest_ext-0.7.0.dist-info/LICENSE
airtest_ext-0.7.0.dist-info/METADATA
airtest_ext-0.7.0.dist-info/WHEEL
airtest_ext-0.7.0.dist-info/top_level.txt
airtest_ext-0.7.0.dist-info/RECORD
